IFS/Applications.py
IFS/Example.py
IFS/ImageSegmentation_Example.py
IFS/PerformanceIndicies.py
IFS/__init__.py
IFS/Measures/Distances.py
IFS/Measures/Miscellaneous.py
IFS/Measures/Similarities.py
IFS/Measures/__init__.py
IFStest/Applications.py
IFStest/Example.py
IFStest/ImageSegmentation_Example.py
IFStest/PerformanceIndicies.py
IFStest/__init__.py
IFStest/Measures/Distances.py
IFStest/Measures/Miscellaneous.py
IFStest/Measures/Similarities.py
IFStest/Measures/__init__.py
IFStest-1.5.dist-info/DESCRIPTION.rst
IFStest-1.5.dist-info/LICENSE.txt
IFStest-1.5.dist-info/METADATA
IFStest-1.5.dist-info/RECORD
IFStest-1.5.dist-info/WHEEL
IFStest-1.5.dist-info/metadata.json
IFStest-1.5.dist-info/top_level.txt
