Metadata-Version: 2.0
Name: IFStest
Version: 1.5
Summary: IFS module
Home-page: http://humain-lab.teiemt.gr/?page_id=2366
Author: Humain Lab
Author-email: test@hotmail.com
License: MIT
Platform: UNKNOWN
Classifier: Development Status :: 4 - Beta
Classifier: License :: OSI Approved :: Python Software Foundation License
Classifier: Programming Language :: Python
Requires-Dist: numpy
